README.rst
setup.py
ebcli/__init__.py
ebcli/boxes.py
ebcli/delete.py
ebcli/deploy.py
ebcli/entrypoint.py
ebcli/export.py
ebcli/export_instance.py
ebcli/get.py
ebcli/import_box.py
ebcli/instances.py
ebcli/login.py
ebcli/logout.py
ebcli/poweron.py
ebcli/reconfigure.py
ebcli/reinstall.py
ebcli/set.py
ebcli/shutdown.py
ebcli/terminate.py
ebcli/workspaces.py
ebcli.egg-info/PKG-INFO
ebcli.egg-info/SOURCES.txt
ebcli.egg-info/dependency_links.txt
ebcli.egg-info/entry_points.txt
ebcli.egg-info/requires.txt
ebcli.egg-info/top_level.txt
ebcli/build/Dockerfile.jinja
ebcli/build/__init__.py